bananas/__init__.py
bananas/environment.py
bananas/lazy.py
bananas/models.py
bananas/py.typed
bananas/query.py
bananas/secrets.py
bananas/settings.py
bananas/url.py
bananas/admin/__init__.py
bananas/admin/extension.py
bananas/admin/i18n.py
bananas/admin/api/__init__.py
bananas/admin/api/mixins.py
bananas/admin/api/permissions.py
bananas/admin/api/router.py
bananas/admin/api/serializers.py
bananas/admin/api/urls.py
bananas/admin/api/versioning.py
bananas/admin/api/views.py
bananas/admin/api/schemas/__init__.py
bananas/admin/api/schemas/base.py
bananas/admin/api/schemas/decorators.py
bananas/admin/api/schemas/yasg.py
bananas/admin/api/v1_0/__init__.py
bananas/admin/api/v1_0/urls.py
bananas/drf/__init__.py
bananas/drf/errors.py
bananas/drf/fencing.py
bananas/drf/utils.py
bananas/management/__init__.py
bananas/management/commands/__init__.py
bananas/management/commands/show_urls.py
bananas/management/commands/syncpermissions.py
bananas/static/admin/bananas/css/bananas.css
bananas/static/admin/bananas/css/banansive.css
bananas/static/admin/bananas/img/django.svg
bananas/static/admin/bananas/img/search.svg
bananas/static/admin/bananas/js/bananas.js
bananas/static/admin/css/responsive.css
bananas/templates/admin/base_site.html
bananas/templates/admin/view.html
django_bananas-2.4.dist-info/licenses/LICENSE
django_bananas-2.4.dist-info/METADATA
django_bananas-2.4.dist-info/WHEEL
django_bananas-2.4.dist-info/top_level.txt
django_bananas-2.4.dist-info/RECORD
